oomclient-0.1.0.dist-info/METADATA
oomclient-0.1.0.dist-info/WHEEL
oomclient/__init__.py
oomclient/oomclient.cpython-38-darwin.so
oomclient-0.1.0.dist-info/RECORD
